pipzap/__init__.py
pipzap/__main__.py
pipzap/cli.py
pipzap/exceptions.py
pipzap/py.typed
pipzap/core/__init__.py
pipzap/core/dependencies.py
pipzap/core/pruner.py
pipzap/core/source_format.py
pipzap/discovery/__init__.py
pipzap/discovery/discover.py
pipzap/discovery/pkg_mapping.json
pipzap/formatting/__init__.py
pipzap/formatting/_uv_to_poetry.py
pipzap/formatting/base.py
pipzap/formatting/conda.py
pipzap/formatting/poetry.py
pipzap/formatting/requirements.py
pipzap/formatting/uv.py
pipzap/parsing/__init__.py
pipzap/parsing/converter.py
pipzap/parsing/parser.py
pipzap/parsing/workspace.py
pipzap/utils/__init__.py
pipzap/utils/debug.py
pipzap/utils/io.py
pipzap/utils/pretty_string.py
pipzap/utils/requirement_string.py
pipzap-0.5.0.dist-info/METADATA
pipzap-0.5.0.dist-info/WHEEL
pipzap-0.5.0.dist-info/entry_points.txt
pipzap-0.5.0.dist-info/licenses/LICENSE
pipzap-0.5.0.dist-info/RECORD
