Metadata-Version: 2.4
Name: pipzap
Version: 0.5.0
Summary: Dependency optimization and pruning made simple
Project-URL: Homepage, https://pypi.org/project/pipzap/
Project-URL: Source, https://github.com/kivicode/pipzap
Author-email: KiviCode <kivicode.dev@gmail.com>
License-Expression: MIT
License-File: LICENSE
Classifier: Development Status :: 4 - Beta
Classifier: Environment :: Console
Classifier: Intended Audience :: Developers
Classifier: License :: OSI Approved :: MIT License
Classifier: Operating System :: OS Independent
Classifier: Programming Language :: Python :: 3
Classifier: Programming Language :: Python :: 3.8
Classifier: Programming Language :: Python :: 3.9
Classifier: Programming Language :: Python :: 3.10
Classifier: Programming Language :: Python :: 3.11
Classifier: Programming Language :: Python :: 3.12
Classifier: Programming Language :: Python :: 3.13
Classifier: Topic :: Software Development :: Build Tools
Classifier: Topic :: Software Development :: Libraries :: Python Modules
Requires-Python: <4.0,>=3.8
Requires-Dist: loguru<0.8,>=0.7.3
Requires-Dist: packaging>=24.2
Requires-Dist: pipreqs>=0.4.13
Requires-Dist: ruamel-yaml>=0.18.16
Requires-Dist: tomlkit>=0.13.2
Requires-Dist: typing-extensions>=4.12.2
Requires-Dist: uv<0.7,>=0.6.9
